odoo8_addon_web_x2many_delete_all-8.0.1.0.0-py2.7-nspkg.pth
odoo_addons/web_x2many_delete_all/__openerp__.py
odoo_addons/web_x2many_delete_all/__init__.py
odoo_addons/web_x2many_delete_all/README.rst
odoo_addons/web_x2many_delete_all/templates/assets.xml
odoo_addons/web_x2many_delete_all/static/src/js/web_x2many_delete_all.js
odoo_addons/web_x2many_delete_all/static/src/css/web_x2many_delete_all.css
odoo_addons/web_x2many_delete_all/static/src/xml/web_x2many_delete_all.xml
odoo8_addon_web_x2many_delete_all-8.0.1.0.0.dist-info/top_level.txt
odoo8_addon_web_x2many_delete_all-8.0.1.0.0.dist-info/WHEEL
odoo8_addon_web_x2many_delete_all-8.0.1.0.0.dist-info/RECORD
odoo8_addon_web_x2many_delete_all-8.0.1.0.0.dist-info/metadata.json
odoo8_addon_web_x2many_delete_all-8.0.1.0.0.dist-info/DESCRIPTION.rst
odoo8_addon_web_x2many_delete_all-8.0.1.0.0.dist-info/METADATA
odoo8_addon_web_x2many_delete_all-8.0.1.0.0.dist-info/namespace_packages.txt
